google_adk_extras/__init__.py
google_adk_extras/adk_builder.py
google_adk_extras/custom_agent_loader.py
google_adk_extras/enhanced_adk_web_server.py
google_adk_extras/enhanced_fastapi.py
google_adk_extras/enhanced_runner.py
google_adk_extras/artifacts/__init__.py
google_adk_extras/artifacts/base_custom_artifact_service.py
google_adk_extras/artifacts/local_folder_artifact_service.py
google_adk_extras/artifacts/mongo_artifact_service.py
google_adk_extras/artifacts/s3_artifact_service.py
google_adk_extras/artifacts/sql_artifact_service.py
google_adk_extras/auth/__init__.py
google_adk_extras/auth/attach.py
google_adk_extras/auth/config.py
google_adk_extras/auth/jwt_utils.py
google_adk_extras/auth/mongo_store.py
google_adk_extras/auth/sql_store.py
google_adk_extras/credentials/base_custom_credential_service.py
google_adk_extras/memory/__init__.py
google_adk_extras/memory/base_custom_memory_service.py
google_adk_extras/memory/mongo_memory_service.py
google_adk_extras/memory/redis_memory_service.py
google_adk_extras/memory/sql_memory_service.py
google_adk_extras/memory/yaml_file_memory_service.py
google_adk_extras/sessions/__init__.py
google_adk_extras/sessions/base_custom_session_service.py
google_adk_extras/sessions/mongo_session_service.py
google_adk_extras/sessions/redis_session_service.py
google_adk_extras/sessions/sql_session_service.py
google_adk_extras/sessions/yaml_file_session_service.py
google_adk_extras/streaming/__init__.py
google_adk_extras/streaming/streaming_controller.py
google_adk_extras/wrappers/artifact_list_wrapper.py
google_adk_extras/wrappers/session_get_wrapper.py
google_adk_extras/wrappers/session_list_wrapper.py
google_adk_extras-0.3.8.dist-info/licenses/LICENSE
google_adk_extras-0.3.8.dist-info/METADATA
google_adk_extras-0.3.8.dist-info/WHEEL
google_adk_extras-0.3.8.dist-info/top_level.txt
google_adk_extras-0.3.8.dist-info/RECORD
