Metadata-Version: 2.4
Name: google-adk-extras
Version: 0.3.8
Summary: Production-ready services and FastAPI wiring for Google ADK
Home-page: https://github.com/DeadMeme5441/google-adk-extras
Author: DeadMeme5441
Author-email: DeadMeme5441 <deadunderscorememe@gmail.com>
Requires-Python: >=3.10,<3.13
License-File: LICENSE
Requires-Dist: google-adk
Requires-Dist: google-genai
Provides-Extra: sql
Requires-Dist: sqlalchemy; extra == "sql"
Provides-Extra: mongodb
Requires-Dist: pymongo>=4.14; extra == "mongodb"
Provides-Extra: redis
Requires-Dist: redis; extra == "redis"
Provides-Extra: yaml
Requires-Dist: pyyaml; extra == "yaml"
Provides-Extra: s3
Requires-Dist: boto3; extra == "s3"
Provides-Extra: jwt
Requires-Dist: PyJWT; extra == "jwt"
Provides-Extra: web
Requires-Dist: fastapi; extra == "web"
Requires-Dist: watchdog; extra == "web"
Provides-Extra: dev
Requires-Dist: pytest; extra == "dev"
Requires-Dist: pytest-asyncio; extra == "dev"
Requires-Dist: build; extra == "dev"
Requires-Dist: twine; extra == "dev"
Provides-Extra: docs
Requires-Dist: mkdocs; extra == "docs"
Requires-Dist: mkdocs-material; extra == "docs"
Requires-Dist: mkdocs-llmstxt; extra == "docs"
Provides-Extra: all
Requires-Dist: google-adk-extras[docs,jwt,mongodb,redis,s3,sql,web,yaml]; extra == "all"
Dynamic: author
Dynamic: home-page
Dynamic: license-file
Dynamic: requires-python
